pycandle/__init__.py
pycandle/general/__init__.py
pycandle/general/experiment.py
pycandle/general/tee.py
pycandle/general/utils.py
pycandle/layers/__init__.py
pycandle/layers/conv.py
pycandle/training/__init__.py
pycandle/training/abstract_callback.py
pycandle/training/callbacks.py
pycandle/training/model_trainer.py
pycandle-1.0.dist-info/LICENSE
pycandle-1.0.dist-info/METADATA
pycandle-1.0.dist-info/WHEEL
pycandle-1.0.dist-info/top_level.txt
pycandle-1.0.dist-info/RECORD
