Metadata-Version: 2.1
Name: pycandle
Version: 1.0
Summary: PyCandle is a lightweight library for pytorch that makes running experiments easy, structured, repeatable and avoids boilerplate code.
Home-page: https://github.com/cschoeller/pycandle
Author: Christoph Schöller
License: UNKNOWN
Platform: UNKNOWN
Classifier: License :: OSI Approved :: MIT License
Requires-Python: >=3.5
Requires-Dist: torch (>=1.2.0)
Requires-Dist: numpy (>=1.16.4)
Requires-Dist: torchvision (>=0.2.1)
Requires-Dist: matplotlib (>=3.0.3)
